LICENSE.txt
README.md
pyproject.toml
aifunctools/__init__.py
aifunctools/openai_funcs.py
aifunctools/parser.py
aifunctools/utils.py
aifunctools.egg-info/PKG-INFO
aifunctools.egg-info/SOURCES.txt
aifunctools.egg-info/dependency_links.txt
aifunctools.egg-info/requires.txt
aifunctools.egg-info/top_level.txt
tests/test_basic.py
tests/test_parser.py