Metadata-Version: 2.1
Name: aifunctools
Version: 0.1.2
Summary: Utilities for AI functions
Author-email: Chang She <chang@lancedb.com>
License:       Apache License
Project-URL: Homepage, https://github.com/lancedb/aifunctools
Project-URL: Bug Reports, https://github.com/lancedb/aifunctools/issues
Project-URL: Source, https://github.com/lancedb/aifunctools/
Keywords: openai,machine learning,gpt functions
Classifier: Development Status :: 3 - Alpha
Classifier: Intended Audience :: Developers
Classifier: Topic :: Scientific/Engineering
Classifier: License :: OSI Approved :: Apache Software License
Classifier: Operating System :: OS Independent
Classifier: Programming Language :: Python :: 3
Classifier: Programming Language :: Python :: 3.8
Classifier: Programming Language :: Python :: 3.9
Classifier: Programming Language :: Python :: 3.10
Classifier: Programming Language :: Python :: 3.11
Classifier: Programming Language :: Python :: 3 :: Only
Requires-Python: >=3.8
Provides-Extra: test
License-File: LICENSE.txt
